simplegit/__init__.py
simplegit/git.py
simplegit-0.0.1.dist-info/DESCRIPTION.rst
simplegit-0.0.1.dist-info/METADATA
simplegit-0.0.1.dist-info/metadata.json
simplegit-0.0.1.dist-info/RECORD
simplegit-0.0.1.dist-info/top_level.txt
simplegit-0.0.1.dist-info/WHEEL
