Metadata-Version: 2.0
Name: simplegit
Version: 0.0.1
Summary: A python module for simple interaction with git via subprocess
Home-page: https://github.com/noahsark769/simplegit
Author: Noah Gilmore
Author-email: noah.w.gilmore@gmail.com
License: MIT
Keywords: git build tools
Platform: UNKNOWN
Classifier: Development Status :: 3 - Alpha
Classifier: Intended Audience :: Developers
Classifier: Topic :: Software Development :: Build Tools
Classifier: License :: OSI Approved :: MIT License
Classifier: Programming Language :: Python :: 2
Classifier: Programming Language :: Python :: 2.6
Classifier: Programming Language :: Python :: 2.7
Classifier: Programming Language :: Python :: 3
Classifier: Programming Language :: Python :: 3.2
Classifier: Programming Language :: Python :: 3.3
Classifier: Programming Language :: Python :: 3.4
Classifier: Programming Language :: Python :: 3.5
